{"CYopDHYEc2SBGXGdM63geQ==\n":"20201109_154525.png-110x112.png","mwWnI02IE0UZ9cSZBB9RDw==\n":"images.jpeg-698x439.jpg","GIvotYp6ifPDt2e94/0qDQ==\n":"images.jpeg-1-698x439.jpg","4GN5JLEnyEMeXIdSFfEgrg==\n":"nasa-q1p7bh3shj8-unsplash.jpg-2000x1330.jpg","my26V2LIxgpApNydXqmXDg==\n":"chuttersnap-gts_eh4g1lk-unsplash.jpg-704x469.jpg","J0S+HbeiMbGPeC2qDQFvvQ==\n":"images (1).jpeg-554x554.jpg","/117wrmxG45kfKMf5tOmSQ==\n":"images (2).jpeg-600x400.jpg","tfIrcf16v+dESergTqu1/A==\n":"mbr_0.jpg-704x1056.jpg","Y6gH23pDDIzJlHxYNtCb2A==\n":"images (3).jpeg-704x330.jpg","u/pyXrZzH98wOVgSNVd5tQ==\n":"559128.jpg-1920x1080.jpg","VYhIm0TDIfpZH23Y+7i8Iw==\n":"international-space-station-1176518.jpg-2000x1330.jpg"}